{
  "maxScore": 15,
  "titles": [
    {
      "minScore": 12,
      "title": "Insightful Connector",
      "description": "You bring thoughtful wisdom to dating—your insights shine!"
    },
    {
      "minScore": 9,
      "title": "Thoughtful Explorer",
      "description": "You’re navigating dating with care and curiosity—keep exploring!"
    },
    {
      "minScore": 6,
      "title": "Hopeful Explorer",
      "description": "You’re on a journey with a hopeful heart—trust your path!"
    },
    {
      "minScore": 3,
      "title": "Curious Starter",
      "description": "You’re just getting started—every step is progress!"
    },
    {
      "minScore": 0,
      "title": "Fresh Starter",
      "description": "Everyone begins somewhere—use these tips to grow your dating confidence."
    }
  ],
  "tipsByArea": {
    "1": [
      "Try to be more open to different types of people. Opposites can complement each other!",
      "Don't put too much pressure on first impressions. Give people a chance to show their true selves.",
      "Consider that there might be many potential matches, not just one 'perfect' person.",
      "Remember that love at first sight is rare - deep connections often take time to develop.",
      "Be open to meeting people outside your usual 'type' - you might be surprised!"
    ],
    "2": [
      "Try updating your profile with recent photos that show your personality.",
      "Be honest in your profile to attract compatible matches.",
      "Don't judge potential matches too quickly based on their profile alone.",
      "Consider that people may present differently online than in person.",
      "Remember that online chemistry doesn't always translate to in-person chemistry."
    ],
    "3": [
      "Be open about your expectations early in the relationship.",
      "Remember that healthy relationships involve compromise from both sides.",
      "Consider that love languages might differ between partners.",
      "Communicate your needs clearly instead of expecting your partner to guess.",
      "Understand that relationships require effort from both people to succeed."
    ],
    "4": [
      "Practice active listening in your conversations.",
      "Try to express your needs clearly and calmly.",
      "Remember that it's okay to take time to process your thoughts before responding.",
      "Avoid making assumptions - ask for clarification when needed.",
      "Use 'I' statements to express how you feel without blaming your partner."
    ],
    "5": [
      "Be open about your long-term goals early in the relationship.",
      "Remember that commitment levels can grow over time.",
      "Consider what you truly want from a long-term partnership.",
      "Discuss important topics like marriage and children when the relationship becomes serious.",
      "Understand that people's goals and priorities can change over time."
    ]
  },
  "defaultTips": [
    "Be yourself and have fun getting to know new people!",
    "Remember that every relationship is a learning experience.",
    "Stay open to new experiences and perspectives.",
    "Trust your instincts when something doesn't feel right.",
    "Don't be too hard on yourself - dating can be challenging for everyone."
  ]
}
